smstrade/__init__.py
smstrade/_version.py
smstrade-0.2.4.dist-info/WHEEL
smstrade-0.2.4.dist-info/top_level.txt
smstrade-0.2.4.dist-info/DESCRIPTION.rst
smstrade-0.2.4.dist-info/METADATA
smstrade-0.2.4.dist-info/RECORD
smstrade-0.2.4.dist-info/metadata.json
smstrade-0.2.4.dist-info/entry_points.txt
