Metadata-Version: 2.0
Name: smstrade
Version: 0.2.4
Summary: a Python library and command line tool to send SMS via the smstrade service.
Home-page: https://gitorious.org/python-smstrade
Author: Jan Dittberner
Author-email: jan@dittberner.info
License: MIT
Platform: UNKNOWN
Classifier: Development Status :: 4 - Beta
Classifier: Environment :: Console
Classifier: Intended Audience :: Developers
Classifier: Intended Audience :: System Administrators
Classifier: License :: OSI Approved :: MIT License
Classifier: Operating System :: OS Independent
Classifier: Programming Language :: Python :: 2
Classifier: Programming Language :: Python :: 2.7
Classifier: Programming Language :: Python :: 3
Classifier: Topic :: Communications
Classifier: Topic :: Software Development :: Libraries :: Python Modules
Classifier: Topic :: Utilities
Requires: requests
Requires: appdirs
